viper/__init__.py
viper_tests-0.2.6.dist-info/LICENSE
viper_tests-0.2.6.dist-info/METADATA
viper_tests-0.2.6.dist-info/WHEEL
viper_tests-0.2.6.dist-info/top_level.txt
viper_tests-0.2.6.dist-info/RECORD
