Metadata-Version: 2.1
Name: viper-tests
Version: 0.2.6
Summary: A modern testing framework
Home-page: UNKNOWN
Author: Aarush Gupta
Author-email: hello@aarushgupta.tk
License: UNKNOWN
Keywords: tests,testing,unittest,viper
Platform: UNKNOWN
Requires-Python: >=3.6
Requires-Dist: colorama
